sfezjfigeuziguezskfigkufesigusefiugsfeigukfikugsekgusigusfeigusekiguf/__init__.py
sfezjfigeuziguezskfigkufesigusefiugsfeigukfikugsekgusigusfeigusekiguf-1.0.0.dist-info/METADATA
sfezjfigeuziguezskfigkufesigusefiugsfeigukfikugsekgusigusfeigusekiguf-1.0.0.dist-info/WHEEL
sfezjfigeuziguezskfigkufesigusefiugsfeigukfikugsekgusigusfeigusekiguf-1.0.0.dist-info/top_level.txt
sfezjfigeuziguezskfigkufesigusefiugsfeigukfikugsekgusigusfeigusekiguf-1.0.0.dist-info/RECORD
